odoo/addons/account_move_so_import/README.rst
odoo/addons/account_move_so_import/__init__.py
odoo/addons/account_move_so_import/__manifest__.py
odoo/addons/account_move_so_import/data/completion_rule_data.xml
odoo/addons/account_move_so_import/i18n/account_move_so_import.pot
odoo/addons/account_move_so_import/i18n/es.po
odoo/addons/account_move_so_import/i18n/hr.po
odoo/addons/account_move_so_import/models/__init__.py
odoo/addons/account_move_so_import/models/account_move.py
odoo/addons/account_move_so_import/readme/CONTRIBUTORS.rst
odoo/addons/account_move_so_import/readme/DESCRIPTION.rst
odoo/addons/account_move_so_import/static/description/icon.png
odoo/addons/account_move_so_import/static/description/index.html
odoo/addons/account_move_so_import/tests/__init__.py
odoo/addons/account_move_so_import/tests/test_completion_so.py
odoo12_addon_account_move_so_import-12.0.1.0.0.99.dev6.dist-info/METADATA
odoo12_addon_account_move_so_import-12.0.1.0.0.99.dev6.dist-info/WHEEL
odoo12_addon_account_move_so_import-12.0.1.0.0.99.dev6.dist-info/top_level.txt
odoo12_addon_account_move_so_import-12.0.1.0.0.99.dev6.dist-info/RECORD
